Metadata-Version: 2.0
Name: odoo8-addon-pos-pricelist
Version: 8.0.1.5.0
Summary: Pricelist for Point of sale
Home-page: UNKNOWN
Author: Adil Houmadi @Taktik, Serv. Tecnol. Avanzados - Pedro M. Baeza, Odoo Community Association (OCA)
Author-email: support@odoo-community.org
License: AGPL-3
Platform: UNKNOWN
Classifier: Programming Language :: Python
Classifier: Framework :: Odoo
Classifier: License :: OSI Approved :: GNU Affero General Public License v3
Requires-Python: ~=2.7
Requires-Dist: odoo (<9.0a,>=8.0a)
